wtforms_sqlalchemy/__init__.py
wtforms_sqlalchemy/fields.py
wtforms_sqlalchemy/orm.py
WTForms_SQLAlchemy-0.4.1.dist-info/LICENSE.txt
WTForms_SQLAlchemy-0.4.1.dist-info/METADATA
WTForms_SQLAlchemy-0.4.1.dist-info/WHEEL
WTForms_SQLAlchemy-0.4.1.dist-info/top_level.txt
WTForms_SQLAlchemy-0.4.1.dist-info/RECORD
