Metadata-Version: 2.1
Name: WTForms-SQLAlchemy
Version: 0.4.1
Summary: SQLAlchemy tools for WTForms
Home-page: http://github.com/wtforms/wtforms-sqlalchemy/
Maintainer: Thomas Johansson, James Crasta
Maintainer-email: wtforms@simplecodes.com
License: BSD
Project-URL: Documentation, https://wtforms-sqlalchemy.readthedocs.io/
Project-URL: Code, https://github.com/wtforms/wtforms-sqlalchemy
Project-URL: Issue Tracker, https://github.com/wtforms/wtforms-sqlalchemy/issues
Classifier: Development Status :: 5 - Production/Stable
Classifier: Environment :: Web Environment
Classifier: Intended Audience :: Developers
Classifier: License :: OSI Approved :: BSD License
Classifier: Operating System :: OS Independent
Classifier: Programming Language :: Python
Classifier: Programming Language :: Python :: 3
Classifier: Programming Language :: Python :: 3.8
Classifier: Programming Language :: Python :: 3.9
Classifier: Programming Language :: Python :: 3.10
Classifier: Programming Language :: Python :: 3.11
Classifier: Programming Language :: Python :: 3.12
Classifier: Topic :: Internet :: WWW/HTTP :: Dynamic Content
Classifier: Topic :: Software Development :: Libraries :: Python Modules
Requires-Python: >=3.8
License-File: LICENSE.txt
Requires-Dist: WTForms>=3.1
Requires-Dist: SQLAlchemy>=1.4
